{"content":[{"id":"60470394","settings":{"flex_direction":"row","flex_gap":{"unit":"px","size":0},"flex_wrap_tablet":"wrap","background_background":"classic","padding":{"unit":"px","top":"70","right":"30","bottom":"20","left":"30","isLinked":false},"padding_mobile":{"unit":"px","top":"70","right":"20","bottom":"20","left":"20","isLinked":false},"__globals__":{"background_color":"globals\/colors?id=a38d833"}},"elements":[{"id":"138905ed","settings":{"flex_direction":"column","content_width":"full","width":{"unit":"%","size":28},"width_tablet":{"unit":"%","size":100,"sizes":[]},"width_mobile":{"unit":"%","size":"","sizes":[]},"padding":{"unit":"px","top":"0","right":"0","bottom":"50","left":"0","isLinked":false}},"elements":[{"id":"cf2d372","settings":{"title":"About","header_size":"h6","typography_typography":"custom","typography_font_family":"Syne","typography_font_size":{"unit":"px","size":20,"sizes":[]},"typography_font_weight":"600","typography_line_height":{"unit":"em","size":1.2,"sizes":[]},"typography_line_height_tablet":{"unit":"px","size":"","sizes":[]},"typography_line_height_mobile":{"unit":"px","size":"","sizes":[]},"typography_letter_spacing":{"unit":"em","size":-0.04,"sizes":[]},"typography_letter_spacing_tablet":{"unit":"em","size":"","sizes":[]},"typography_letter_spacing_mobile":{"unit":"em","size":"","sizes":[]},"_margin":{"unit":"px","top":"0","right":"0","bottom":"0","left":"0","isLinked":false},"_flex_align_self":"flex-start","_css_classes":"sub-title","__globals__":{"title_color":"globals\/colors?id=372884b"}},"elements":[],"isInner":false,"widgetType":"heading","elType":"widget"},{"id":"73cae027","settings":{"editor":"<p>Lorem ipsum dolor sit amet, consect etur adi pisicing elit sed do eiusmod tempor incididunt ut labore.<\/p>","text_color":"#8D869D","_margin":{"unit":"px","top":"15","right":"0","bottom":"0","left":"0","isLinked":false}},"elements":[],"isInner":false,"widgetType":"text-editor","elType":"widget"},{"id":"589c032e","settings":{"social_icon_list":[{"social_icon":{"value":"fab fa-facebook-f","library":"fa-brands"},"_id":"08b6783","link":{"url":"#","is_external":"true","nofollow":"","custom_attributes":""}},{"social_icon":{"value":"fab fa-twitter","library":"fa-brands"},"_id":"3bab1e2","link":{"url":"#","is_external":"true","nofollow":"","custom_attributes":""}},{"social_icon":{"value":"fab fa-youtube","library":"fa-brands"},"_id":"8716f36","link":{"url":"#","is_external":"true","nofollow":"","custom_attributes":""}},{"social_icon":{"value":"fab fa-instagram","library":"fa-brands"},"_id":"24d6c55","link":{"url":"#","is_external":"true","nofollow":"","custom_attributes":""}}],"shape":"circle","align":"left","icon_color":"custom","icon_primary_color":"#30283F","icon_size":{"unit":"px","size":14,"sizes":[]},"icon_padding":{"unit":"em","size":1,"sizes":[]},"icon_spacing":{"unit":"px","size":10,"sizes":[]}},"elements":[],"isInner":false,"widgetType":"social-icons","elType":"widget"}],"isInner":false,"elType":"container"},{"id":"185c5171","settings":{"flex_direction":"column","content_width":"full","width":{"unit":"%","size":22},"width_tablet":{"unit":"%","size":30,"sizes":[]},"width_mobile":{"unit":"%","size":"","sizes":[]},"margin":{"unit":"px","top":"0","right":"0","bottom":"50","left":"0","isLinked":false},"padding":{"unit":"px","top":"0","right":"30","bottom":"0","left":"60","isLinked":false},"padding_tablet":{"unit":"px","top":"0","right":"20","bottom":"0","left":"0","isLinked":false}},"elements":[{"id":"45cd9853","settings":{"title":"Explore","header_size":"h6","typography_typography":"custom","typography_font_family":"Syne","typography_font_size":{"unit":"px","size":20,"sizes":[]},"typography_font_weight":"600","typography_line_height":{"unit":"em","size":1.2,"sizes":[]},"typography_line_height_tablet":{"unit":"px","size":"","sizes":[]},"typography_line_height_mobile":{"unit":"px","size":"","sizes":[]},"typography_letter_spacing":{"unit":"em","size":-0.04,"sizes":[]},"typography_letter_spacing_tablet":{"unit":"em","size":"","sizes":[]},"typography_letter_spacing_mobile":{"unit":"em","size":"","sizes":[]},"_margin":{"unit":"px","top":"0","right":"0","bottom":"0","left":"0","isLinked":false},"_flex_align_self":"flex-start","_css_classes":"sub-title","__globals__":{"title_color":"globals\/colors?id=372884b"}},"elements":[],"isInner":false,"widgetType":"heading","elType":"widget"},{"id":"1360585a","settings":{"icon_list":[{"text":"About Company","selected_icon":{"value":"","library":""},"_id":"6fe08cd","link":{"url":"#","is_external":"","nofollow":"","custom_attributes":""}},{"text":"Meet the Team","selected_icon":{"value":"","library":""},"_id":"f3c5213","link":{"url":"#","is_external":"","nofollow":"","custom_attributes":""}},{"text":"News & Media","selected_icon":{"value":"","library":""},"_id":"0c2f0c4","link":{"url":"#","is_external":"","nofollow":"","custom_attributes":""}},{"text":"Our Projects","selected_icon":{"value":"","library":""},"_id":"0c413de","link":{"url":"#","is_external":"","nofollow":"","custom_attributes":""}},{"text":"Contact","selected_icon":{"value":"","library":""},"_id":"f45fcde","link":{"url":"#","is_external":"","nofollow":"","custom_attributes":""}}],"space_between":{"unit":"px","size":8,"sizes":[]},"icon_typography_typography":"custom","icon_typography_font_family":"DM Sans","icon_typography_font_size":{"unit":"px","size":15,"sizes":[]},"icon_typography_font_weight":"400","icon_typography_line_height":{"unit":"px","size":28,"sizes":[]},"text_color":"#8D869D","_margin":{"unit":"px","top":"15","right":"0","bottom":"0","left":"0","isLinked":false},"__globals__":{"text_color_hover":"globals\/colors?id=372884b"}},"elements":[],"isInner":false,"widgetType":"icon-list","elType":"widget"}],"isInner":false,"elType":"container"},{"id":"60e713d4","settings":{"flex_direction":"column","content_width":"full","width":{"unit":"%","size":28},"width_tablet":{"unit":"%","size":40,"sizes":[]},"width_mobile":{"unit":"%","size":"","sizes":[]},"margin":{"unit":"px","top":"0","right":"0","bottom":"50","left":"0","isLinked":false},"padding":{"unit":"px","top":"0","right":"60","bottom":"0","left":"0","isLinked":false},"padding_tablet":{"unit":"px","top":"0","right":"0","bottom":"0","left":"0","isLinked":false}},"elements":[{"id":"d997ad1","settings":{"title":"Portfolio","header_size":"h6","typography_typography":"custom","typography_font_family":"Syne","typography_font_size":{"unit":"px","size":20,"sizes":[]},"typography_font_weight":"600","typography_line_height":{"unit":"em","size":1.2,"sizes":[]},"typography_line_height_tablet":{"unit":"px","size":"","sizes":[]},"typography_line_height_mobile":{"unit":"px","size":"","sizes":[]},"typography_letter_spacing":{"unit":"em","size":-0.04,"sizes":[]},"typography_letter_spacing_tablet":{"unit":"em","size":"","sizes":[]},"typography_letter_spacing_mobile":{"unit":"em","size":"","sizes":[]},"_margin":{"unit":"px","top":"0","right":"0","bottom":"0","left":"0","isLinked":false},"_flex_align_self":"flex-start","_css_classes":"sub-title","__globals__":{"title_color":"globals\/colors?id=372884b"}},"elements":[],"isInner":false,"widgetType":"heading","elType":"widget"},{"id":"1f960bb5","settings":{"flex_direction":"row","flex_justify_content":"flex-start","flex_justify_content_tablet":"flex-start","flex_justify_content_mobile":"flex-start","flex_gap":{"unit":"px","size":5,"sizes":[]},"flex_gap_tablet":{"unit":"px","size":5,"sizes":[]},"flex_wrap":"wrap","margin":{"unit":"px","top":"15","right":"0","bottom":"0","left":"0","isLinked":false}},"elements":[{"id":"215cba35","settings":{"image":{"url":"https:\/\/kitpapa.net\/nexus\/wp-content\/uploads\/2023\/08\/project-thumb-1.jpg","id":1269,"size":"","alt":"","source":"library"},"width":{"unit":"%","size":100,"sizes":[]},"_margin":{"unit":"px","top":"0","right":"0","bottom":"0","left":"0","isLinked":false},"link_to":"custom","link":{"url":"#","is_external":"","nofollow":"","custom_attributes":""}},"elements":[],"isInner":false,"widgetType":"image","elType":"widget"},{"id":"1dd55774","settings":{"image":{"url":"https:\/\/kitpapa.net\/nexus\/wp-content\/uploads\/2023\/08\/project-thumb-2.jpg","id":1270,"size":"","alt":"","source":"library"},"width":{"unit":"%","size":100,"sizes":[]},"_margin":{"unit":"px","top":"0","right":"0","bottom":"0","left":"0","isLinked":false},"link_to":"custom","link":{"url":"#","is_external":"","nofollow":"","custom_attributes":""}},"elements":[],"isInner":false,"widgetType":"image","elType":"widget"},{"id":"4aa1ddbe","settings":{"image":{"url":"https:\/\/kitpapa.net\/nexus\/wp-content\/uploads\/2023\/08\/project-thumb-3.jpg","id":1271,"size":"","alt":"","source":"library"},"width":{"unit":"%","size":100,"sizes":[]},"_margin":{"unit":"px","top":"0","right":"0","bottom":"0","left":"0","isLinked":false},"link_to":"custom","link":{"url":"#","is_external":"","nofollow":"","custom_attributes":""}},"elements":[],"isInner":false,"widgetType":"image","elType":"widget"},{"id":"568fef14","settings":{"image":{"url":"https:\/\/kitpapa.net\/nexus\/wp-content\/uploads\/2023\/08\/project-thumb-4-1.jpg","id":1275,"size":"","alt":"","source":"library"},"link_to":"custom","link":{"url":"#","is_external":"","nofollow":"","custom_attributes":""}},"elements":[],"isInner":false,"widgetType":"image","elType":"widget"},{"id":"3b23b5e9","settings":{"image":{"url":"https:\/\/kitpapa.net\/nexus\/wp-content\/uploads\/2023\/08\/project-thumb-5-1.jpg","id":1276,"size":"","alt":"","source":"library"},"link_to":"custom","link":{"url":"#","is_external":"","nofollow":"","custom_attributes":""}},"elements":[],"isInner":false,"widgetType":"image","elType":"widget"},{"id":"42685cca","settings":{"image":{"url":"https:\/\/kitpapa.net\/nexus\/wp-content\/uploads\/2023\/08\/project-thumb-6-1.jpg","id":1277,"size":"","alt":"","source":"library"},"link_to":"custom","link":{"url":"#","is_external":"","nofollow":"","custom_attributes":""}},"elements":[],"isInner":false,"widgetType":"image","elType":"widget"}],"isInner":false,"elType":"container"}],"isInner":false,"elType":"container"},{"id":"67a91b17","settings":{"flex_direction":"column","content_width":"full","width":{"unit":"%","size":22},"width_tablet":{"unit":"%","size":30,"sizes":[]},"width_mobile":{"unit":"%","size":"","sizes":[]},"margin":{"unit":"px","top":"0","right":"0","bottom":"50","left":"0","isLinked":false},"padding_tablet":{"unit":"px","top":"0","right":"0","bottom":"0","left":"20","isLinked":false},"padding_mobile":{"unit":"px","top":"0","right":"0","bottom":"0","left":"0","isLinked":false}},"elements":[{"id":"53eba17a","settings":{"title":"Portfolio","header_size":"h6","typography_typography":"custom","typography_font_family":"Syne","typography_font_size":{"unit":"px","size":20,"sizes":[]},"typography_font_weight":"600","typography_line_height":{"unit":"em","size":1.2,"sizes":[]},"typography_line_height_tablet":{"unit":"px","size":"","sizes":[]},"typography_line_height_mobile":{"unit":"px","size":"","sizes":[]},"typography_letter_spacing":{"unit":"em","size":-0.04,"sizes":[]},"typography_letter_spacing_tablet":{"unit":"em","size":"","sizes":[]},"typography_letter_spacing_mobile":{"unit":"em","size":"","sizes":[]},"_margin":{"unit":"px","top":"0","right":"0","bottom":"0","left":"0","isLinked":false},"_flex_align_self":"flex-start","_css_classes":"sub-title","__globals__":{"title_color":"globals\/colors?id=372884b"}},"elements":[],"isInner":false,"widgetType":"heading","elType":"widget"},{"id":"41ba927b","settings":{"title":"66 Road Broklyn Street, 600<br>\nNew York, USA\n","header_size":"span","title_color":"#878197","typography_typography":"custom","typography_font_family":"DM Sans","typography_font_size":{"unit":"px","size":16,"sizes":[]},"typography_font_weight":"400","typography_line_height":{"unit":"px","size":30,"sizes":[]},"_margin":{"unit":"px","top":"15","right":"0","bottom":"20","left":"0","isLinked":false},"__globals__":{"typography_typography":""}},"elements":[],"isInner":false,"widgetType":"heading","elType":"widget"},{"id":"274221ad","settings":{"icon_list":[{"text":"info@nexus.com","selected_icon":{"value":"fas fa-envelope","library":"fa-solid"},"_id":"6fe08cd","link":{"url":"mail:info@nexus.com","is_external":"","nofollow":"","custom_attributes":""}},{"text":"+92 666 888 0000","selected_icon":{"value":"fas fa-phone-square-alt","library":"fa-solid"},"link":{"url":"tel:+92 666 888 0000","is_external":"","nofollow":"","custom_attributes":""},"_id":"0c2f0c4"}],"space_between":{"unit":"px","size":10,"sizes":[]},"icon_color":"#7243F2","icon_size":{"unit":"px","size":16,"sizes":[]},"text_indent":{"unit":"px","size":6,"sizes":[]},"icon_typography_typography":"custom","icon_typography_font_family":"DM Sans","icon_typography_font_size":{"unit":"px","size":16,"sizes":[]},"icon_typography_font_weight":"400","icon_typography_line_height":{"unit":"px","size":28,"sizes":[]},"text_color":"#FFFFFF","text_color_hover":"#8D869D","_margin":{"unit":"px","top":"0","right":"0","bottom":"0","left":"0","isLinked":false},"__globals__":{"text_color_hover":"","text_color":"globals\/colors?id=372884b","icon_color":"globals\/colors?id=secondary"}},"elements":[],"isInner":false,"widgetType":"icon-list","elType":"widget"}],"isInner":false,"elType":"container"}],"isInner":false,"elType":"container"},{"id":"32fa286b","settings":{"flex_direction":"column","background_background":"classic","border_border":"solid","border_width":{"unit":"px","top":"1","right":"0","bottom":"0","left":"0","isLinked":false},"border_color":"#FFFFFF1A","padding":{"unit":"px","top":"35","right":"20","bottom":"35","left":"20","isLinked":false},"__globals__":{"background_color":"globals\/colors?id=a38d833"}},"elements":[{"id":"3efbb84a","settings":{"title":"\u00a9 Copyright 2023 by nexus.com","header_size":"span","align":"center","title_color":"#8F8F8F","typography_typography":"custom","typography_font_family":"DM Sans","typography_font_size":{"unit":"px","size":16,"sizes":[]},"typography_font_weight":"400","typography_line_height":{"unit":"px","size":30,"sizes":[]},"__globals__":{"typography_typography":""}},"elements":[],"isInner":false,"widgetType":"heading","elType":"widget"}],"isInner":false,"elType":"container"},{"id":"4229b5f0","settings":{"flex_direction":"column"},"elements":[{"id":"699b7109","settings":{"html":"<style>\n\n:root{\n    --theme-color1: #ae8fff;\n    --theme-color2: #7243f2;\n    --theme-color3: #ffffff;\n    --theme-color4: #1d1729;\n    --bg-theme-color2: #7243f2;\n    --gradient-1: linear-gradient(to left, #ae8fff, #7243f2);\n}\n\n\n.sub-title .elementor-heading-title:before {\n    position: absolute;\n    left: 100%;\n    top: 50%;\n    margin-top: -1px;\n    height: 2px;\n    width: 26px;\n    margin-left: 10px;\n    background: var(--gradient-1);\n    content: \"\";\n}\n\n.sub-title .elementor-heading-title:after {\n    position: absolute;\n    left: 100%;\n    top: 50%;\n    margin-top: -3px;\n    height: 6px;\n    width: 6px;\n    margin-left: 36px;\n    background: var(--gradient-1);\n    content: \"\";\n    border-radius: 50%;\n}\n    \n    \n<\/style>"},"elements":[],"isInner":false,"widgetType":"html","elType":"widget"}],"isInner":false,"elType":"container"}],"page_settings":{"eael_ext_toc_title":"Table of Contents"},"version":"0.4","title":"Footer","type":"page"}